{"packages":{"orchid/cms":[{"name":"orchid/cms","description":"Press package for Orchid Platform","keywords":["blog","cms","laravel","platform","press","orchid"],"homepage":"https://orchid.software","version":"1.4.0","version_normalized":"1.4.0.0","license":["MIT"],"authors":[{"name":"Alexandr Chernyaev","email":"bliz48rus@gmail.com"},{"name":"Pavel Salador","email":"Salador2005@yandex.ru"}],"source":{"type":"git","url":"https://github.com/orchidcommunity/press.git","reference":"ffd3d0f393eb26acccbf14baa16dec061a563b0b"},"dist":{"type":"zip","url":"https://api.github.com/repos/orchidcommunity/press/zipball/ffd3d0f393eb26acccbf14baa16dec061a563b0b","reference":"ffd3d0f393eb26acccbf14baa16dec061a563b0b","shasum":""},"type":"library","time":"2020-06-19T12:46:43+00:00","autoload":{"psr-4":{"Orchid\\Database\\Press\\Seeds\\":"database/seeds/","Orchid\\Press\\":"src/"},"files":["src/Support/helpers.php"]},"extra":{"laravel":{"providers":["Orchid\\Press\\Providers\\PressServiceProvider"]}},"require":{"cviebrock/eloquent-sluggable":"^7.0","orchid/platform":"^7.0|dev-master"},"abandoned":"orchid/press","support":{"issues":"https://github.com/orchidcommunity/press/issues","source":"https://github.com/orchidcommunity/press/tree/1.4.0"}},{"version":"1.3.0","version_normalized":"1.3.0.0","source":{"type":"git","url":"https://github.com/orchidcommunity/press.git","reference":"879254aa2620f582db67e30a31a097875a62b246"},"dist":{"type":"zip","url":"https://api.github.com/repos/orchidcommunity/press/zipball/879254aa2620f582db67e30a31a097875a62b246","reference":"879254aa2620f582db67e30a31a097875a62b246","shasum":""},"time":"2019-10-06T10:12:23+00:00","require":{"php":"^7.1","cviebrock/eloquent-sluggable":"^6.0","orchid/platform":"^6.0|dev-master","orchids/xsetting":"dev-master"},"require-dev":{"fzaninotto/faker":"^1.4","mockery/mockery":"~1.0","orchestra/testbench":"~3.8.0","phpunit/php-code-coverage":"^6.0|^7.0","phpunit/phpunit":"^7.5|^8.0"},"support":{"issues":"https://github.com/orchidcommunity/press/issues","source":"https://github.com/orchidcommunity/press/tree/1.3.0"}},{"version":"1.2.2","version_normalized":"1.2.2.0","source":{"type":"git","url":"https://github.com/orchidcommunity/press.git","reference":"9e6b017f4b2144e169b13feb3c5fb9bda3c0f691"},"dist":{"type":"zip","url":"https://api.github.com/repos/orchidcommunity/press/zipball/9e6b017f4b2144e169b13feb3c5fb9bda3c0f691","reference":"9e6b017f4b2144e169b13feb3c5fb9bda3c0f691","shasum":""},"time":"2019-07-24T09:28:16+00:00","autoload":{"psr-4":{"Orchid\\Database\\Press\\Seeds\\":"database/seeds/","Orchid\\Press\\":"src/"}},"require":{"php":"^7.1","cviebrock/eloquent-sluggable":"^4.8","orchid/platform":"^5.1","orchids/xsetting":"dev-master"},"support":{"issues":"https://github.com/orchidcommunity/press/issues","source":"https://github.com/orchidcommunity/press/tree/1.2.2"}},{"version":"1.2.1","version_normalized":"1.2.1.0","source":{"type":"git","url":"https://github.com/orchidsoftware/press.git","reference":"9fd83025388909d80020ab673e5c1638ed7c24b2"},"dist":{"type":"zip","url":"https://api.github.com/repos/orchidsoftware/press/zipball/9fd83025388909d80020ab673e5c1638ed7c24b2","reference":"9fd83025388909d80020ab673e5c1638ed7c24b2","shasum":""},"time":"2019-06-05T09:15:01+00:00","require":{"php":"^7.1","cviebrock/eloquent-sluggable":"^4.8","orchid/platform":"~5.0.0|dev-master","orchids/xsetting":"dev-master"},"support":{"issues":"https://github.com/orchidsoftware/press/issues","source":"https://github.com/orchidsoftware/press/tree/1.2.1"}},{"version":"1.2.0","version_normalized":"1.2.0.0","source":{"type":"git","url":"https://github.com/orchidsoftware/press.git","reference":"100bed7ca6cd076b7d4e26fad154ff4da6a9c482"},"dist":{"type":"zip","url":"https://api.github.com/repos/orchidsoftware/press/zipball/100bed7ca6cd076b7d4e26fad154ff4da6a9c482","reference":"100bed7ca6cd076b7d4e26fad154ff4da6a9c482","shasum":""},"time":"2019-06-05T08:45:01+00:00","support":{"issues":"https://github.com/orchidsoftware/press/issues","source":"https://github.com/orchidsoftware/press/tree/1.2.0"}},{"description":"Laravel CMS for website.","keywords":["log","framework","menu","cms","crud","scaffold","laravel","Settings","platform","website","orchid"],"homepage":"http://orchid.software","version":"1.1.4","version_normalized":"1.1.4.0","authors":[{"name":"Alexandr Chernyaev","email":"bliz48rus@gmail.com"}],"source":{"type":"git","url":"https://github.com/orchidsoftware/press.git","reference":"864e54e734af340b58ba78cb73d5c7ceb745930a"},"dist":{"type":"zip","url":"https://api.github.com/repos/orchidsoftware/press/zipball/864e54e734af340b58ba78cb73d5c7ceb745930a","reference":"864e54e734af340b58ba78cb73d5c7ceb745930a","shasum":""},"time":"2018-09-05T13:22:03+00:00","autoload":{"psr-4":{"Orchid\\CMS\\":"src/"}},"extra":{"laravel":{"providers":["Orchid\\CMS\\Providers\\FoundationServiceProvider"]}},"require":{"php":">=7.0","orchid/platform":"^1.0","orchid/settings":"^2.0","orchid/log":"^1.0","orchid/monitor":"^1.0","intervention/image":"^2.3","cartalyst/tags":"^5.0","cviebrock/eloquent-sluggable":"^4.2","spatie/laravel-backup":"^5.0","teamtnt/laravel-scout-tntsearch-driver":"^3.0"},"require-dev":{"mockery/mockery":"~0.9.4","phpunit/phpunit":"~6.0","orchestra/testbench":"~3.0"},"suggest":{"orchid/socket":"Laravel library for asynchronously serving WebSockets."},"support":{"issues":"https://github.com/theOrchid/Platform/issues","source":"https://github.com/theOrchid/Platform"}},{"version":"1.1.3","version_normalized":"1.1.3.0","source":{"type":"git","url":"https://github.com/TheOrchid/CMS.git","reference":"e53fa2792f7292028ce04771e56ff430cd18353e"},"dist":{"type":"zip","url":"https://api.github.com/repos/TheOrchid/CMS/zipball/e53fa2792f7292028ce04771e56ff430cd18353e","reference":"e53fa2792f7292028ce04771e56ff430cd18353e","shasum":""},"time":"2017-09-05T23:50:03+00:00","require":{"php":">=7.0","orchid/platform":"^1.0","orchid/settings":"^2.0","orchid/log":"^1.0","orchid/monitor":"^1.0","intervention/image":"^2.3","cartalyst/tags":"^5.0","cviebrock/eloquent-sluggable":"^4.2","spatie/laravel-backup":"^5.0"}},{"version":"1.1.2","version_normalized":"1.1.2.0","source":{"type":"git","url":"https://github.com/TheOrchid/CMS.git","reference":"2e1c7cfc898b5247d8209d44f9c3501f47609eb8"},"dist":{"type":"zip","url":"https://api.github.com/repos/TheOrchid/CMS/zipball/2e1c7cfc898b5247d8209d44f9c3501f47609eb8","reference":"2e1c7cfc898b5247d8209d44f9c3501f47609eb8","shasum":""},"time":"2017-09-03T16:24:54+00:00"},{"version":"1.1.1","version_normalized":"1.1.1.0","source":{"type":"git","url":"https://github.com/TheOrchid/CMS.git","reference":"16f9f631c3d2f0bf2e09df013553cbb1d7d49d24"},"dist":{"type":"zip","url":"https://api.github.com/repos/TheOrchid/CMS/zipball/16f9f631c3d2f0bf2e09df013553cbb1d7d49d24","reference":"16f9f631c3d2f0bf2e09df013553cbb1d7d49d24","shasum":""},"time":"2017-08-31T16:21:44+00:00"},{"version":"1.1","version_normalized":"1.1.0.0","source":{"type":"git","url":"https://github.com/TheOrchid/CMS.git","reference":"2e34a55060d230dc32e5b3abe64c1557c2be4eec"},"dist":{"type":"zip","url":"https://api.github.com/repos/TheOrchid/CMS/zipball/2e34a55060d230dc32e5b3abe64c1557c2be4eec","reference":"2e34a55060d230dc32e5b3abe64c1557c2be4eec","shasum":""},"time":"2017-08-31T14:57:10+00:00"},{"homepage":"https://theorchid.github.io/","version":"1.0.1","version_normalized":"1.0.1.0","source":{"type":"git","url":"https://github.com/TheOrchid/CMS.git","reference":"ba32345e2538b218d5f8cb308be9430633b12770"},"dist":{"type":"zip","url":"https://api.github.com/repos/TheOrchid/CMS/zipball/ba32345e2538b218d5f8cb308be9430633b12770","reference":"ba32345e2538b218d5f8cb308be9430633b12770","shasum":""},"time":"2017-08-21T22:06:28+00:00","require":{"php":">=7.0","orchid/platform":"^1.0","orchid/settings":"^2.0","orchid/log":"^1.0","orchid/monitor":"^1.0","intervention/image":"^2.3","cartalyst/tags":"^4.0","cviebrock/eloquent-sluggable":"^4.2","spatie/laravel-backup":"4.*"}},{"version":"1.0","version_normalized":"1.0.0.0","source":{"type":"git","url":"https://github.com/TheOrchid/CMS.git","reference":"e86ad01b55ee7270e861a54a0973316486be3f71"},"dist":{"type":"zip","url":"https://api.github.com/repos/TheOrchid/CMS/zipball/e86ad01b55ee7270e861a54a0973316486be3f71","reference":"e86ad01b55ee7270e861a54a0973316486be3f71","shasum":""},"time":"2017-08-21T22:04:30+00:00","require":{"php":">=7.0","orchid/platform":"1.0.x-dev","orchid/settings":"^2.0","orchid/log":"^1.0","orchid/monitor":"^1.0","intervention/image":"^2.3","cartalyst/tags":"^4.0","cviebrock/eloquent-sluggable":"^4.2","spatie/laravel-backup":"4.*"}}]},"minified":"composer/2.0","last-modified":"Tue, 15 Sep 2020 11:04:04 GMT"}